pysdr
