Metadata-Version: 1.1
Name: pysdr
Version: 1.2
Summary: A software-defined radio (SDR) framework
Home-page: https://github.com/pysdr/pysdr
Author: Marc L
Author-email: 777arc@vt.edu
License: GPL-3.0
Keywords: software-defind radio dsp sdr digital signal processing wireless communications
Platform: UNKNOWN
Classifier: Development Status :: 1 - Planning
Classifier: Intended Audience :: Science/Research
Classifier: Topic :: Scientific/Engineering
Classifier: License :: OSI Approved :: GNU General Public License v3 (GPLv3)
Classifier: Programming Language :: Python :: 3
